dlkoopman/__init__.py
dlkoopman/config.py
dlkoopman/hyp_search.py
dlkoopman/metrics.py
dlkoopman/nets.py
dlkoopman/state_pred.py
dlkoopman/traj_pred.py
dlkoopman/utils.py
dlkoopman-1.2.1.dist-info/METADATA
dlkoopman-1.2.1.dist-info/WHEEL
dlkoopman-1.2.1.dist-info/licenses/LICENSE
dlkoopman-1.2.1.dist-info/RECORD
