Metadata-Version: 2.4
Name: dlkoopman
Version: 1.2.1
Summary: A general-purpose Python package for Koopman theory using deep learning.
License: MIT
License-File: LICENSE
Keywords: koopman theory,koopman operator,deep learning,autoencoder
Author: Sourya Dey
Author-email: sourya@galois.com
Maintainer: Galois dlkoopman team
Maintainer-email: dlkoopman@galois.com
Requires-Python: >=3.9,<4.0
Classifier: License :: OSI Approved :: MIT License
Classifier: Programming Language :: Python :: 3
Classifier: Programming Language :: Python :: 3.9
Classifier: Programming Language :: Python :: 3.10
Classifier: Programming Language :: Python :: 3.11
Classifier: Programming Language :: Python :: 3.12
Classifier: Programming Language :: Python :: 3.13
Classifier: Programming Language :: Python :: 3.14
Classifier: Topic :: Scientific/Engineering :: Artificial Intelligence
Classifier: Topic :: Scientific/Engineering :: Physics
Requires-Dist: matplotlib (>=3.4.2,<4.0.0)
Requires-Dist: numpy (>=1.23.0,<2.0.0)
Requires-Dist: pandas (>=1.2.3)
Requires-Dist: shortuuid (>=1.0.9,<2.0.0)
Requires-Dist: torch (>=1.12.1)
Requires-Dist: tqdm (>=4.61.1,<5.0.0)
Project-URL: Documentation, https://galoisinc.github.io/dlkoopman/
Project-URL: Repository, https://github.com/GaloisInc/dlkoopman
